{"paperId": "1a9520fc9779caf537099fd83c87d62e116c8b2c", "publicationVenue": {"id": "74b08738-109e-45e9-b689-13368a2fca8b", "name": "Cybernetics and systems", "type": "journal", "alternate_names": ["Cybern Syst", "Cybernetics and Systems", "Cybern syst"], "issn": "0196-9722", "url": "http://www.catchword.com/rpsv/catchword/tandf/01969722/contp1-1.htm", "alternate_urls": ["http://www.tandfonline.com/loi/ucbs20", "http://www.informaworld.com/openurl?genre=journal&issn=0196-9722", "http://figaro.catchword.com/rpsv/catchword/tandf/01969722/contp1-1.htm", "http://www.tandfonline.com/action/aboutThisJournal?journalCode=ucbs20", "http://www.metapress.com/openurl.asp?genre=journal&issn=0196-9722"]}, "title": "Improving Landslides Prediction: Meteorological Data Preprocessing Based on Supervised and Unsupervised Learning", "abstract": null, "venue": "Cybernetics and systems", "year": 2023, "fieldsOfStudy": null, "publicationTypes": ["JournalArticle"], "publicationDate": "2023-11-07", "journal": {"name": "Cybernetics and Systems"}, "authors": [{"authorId": "2226076051", "name": "B. Guerrero-Rodriguez"}, {"authorId": "1410449122", "name": "Jaime Salvador-Meneses"}, {"authorId": "2265872032", "name": "Jose Garcia-Rodriguez"}, {"authorId": "2222749075", "name": "Christian Mejia-Escobar"}], "citations": []}
