{"paperId": "39b055ef2460926ba0e1a3ef64d4da816ac5d93a", "publicationVenue": null, "title": "In-Memory Deep Learning Computations on GPUs for Prediction of Road Traffic Incidents Using Big Data Fusion", "abstract": null, "venue": "Smart Infrastructure and Applications", "year": 2019, "fieldsOfStudy": ["Computer Science"], "publicationTypes": null, "publicationDate": null, "journal": {"name": "Smart Infrastructure and Applications"}, "authors": [{"authorId": "3121734", "name": "M. Aqib"}, {"authorId": "39799687", "name": "Rashid Mehmood"}, {"authorId": "103375638", "name": "Ahmed Alzahrani"}, {"authorId": "2574028", "name": "Iyad A. Katib"}], "citations": [{"paperId": "ac27880833dc3bab54cb57270ec91cf8c5776784", "title": "Challenges and Opportunities of Using Data Fusion Methods for Travel Time Estimation"}, {"paperId": "e2a5d8824f12b14a4599e9c0d2864fbd98e0f4a7", "title": "Deep Journalism and DeepJournal V1.0: A Data-Driven Deep Learning Approach to Discover Parameters for Transportation"}, {"paperId": "157600e0348b99bbc4187b95fd0c438a2189a841", "title": "Imtidad: A Reference Architecture and a Case Study on Developing Distributed AI Services for Skin Disease Diagnosis over Cloud, Fog and Edge"}, {"paperId": "4692960b0423e297fe9404d0315a899dbcac7357", "title": "Data science and Machine learning in the Clouds: A Perspective for the Future"}, {"paperId": "54038f406ddf4e30256b9095cf88f36dcbae77b5", "title": "Cloud Big Data Mining and Analytics: Bringing Greenness and Acceleration in the Cloud"}, {"paperId": "f986edb93a6af37296efdafbe715657d49e04f2a", "title": "Can Building \u201cArtificially Intelligent Cities\u201d Safeguard Humanity from Natural Disasters, Pandemics, and Other Catastrophes? An Urban Scholar\u2019s Perspective"}, {"paperId": "17f43a1a979d2d8d76229ba104a2367523496452", "title": "TAAWUN: a Decision Fusion and Feature Specific Road Detection Approach for Connected Autonomous Vehicles"}, {"paperId": "304944549ddc3c08c401ddd3c4b2faafc1c2d7e9", "title": "Rapid Transit Systems: Smarter Urban Planning Using Big Data, In-Memory Computing, Deep Learning, and GPUs"}, {"paperId": "f4645c1fe6644a285b2afc05e36fb5b89959a5d4", "title": "Review of Data Fusion Methods for Real-Time and Multi-Sensor Traffic Flow Analysis"}, {"paperId": "dcb9cdb2d8181dd48311387c619006ec61602dd6", "title": "Road Traffic Vehicle Detection and Tracking using Deep Learning with Custom-Collected and Public Datasets"}]}
