{"paperId": "43acfdfbc48554165c63378610d71bedf6da355a", "publicationVenue": null, "title": "A grouping-attention convolutional neural network for performance degradation estimation of high-speed train lateral damper", "abstract": null, "venue": "Applied intelligence (Boston)", "year": 2022, "fieldsOfStudy": ["Computer Science"], "publicationTypes": ["JournalArticle"], "publicationDate": "2022-04-20", "journal": {"name": "Applied Intelligence", "pages": "658-682", "volume": "53"}, "authors": [{"authorId": "2049666629", "name": "Junxiao Ren"}, {"authorId": "1743146", "name": "Wei-dong Jin"}, {"authorId": "80611592", "name": "Yunpu Wu"}, {"authorId": "2157903642", "name": "Zhang Sun"}], "citations": [{"paperId": "c99a95e398497fd7b4eb946937d7e0486a5fda6f", "title": "Enabling inductive knowledge graph completion via structure-aware attention network"}, {"paperId": "9c300da2e85c9d9bef5553f045cf9b4228eefbab", "title": "Research on Performance Degradation Estimation of Key Components of High-Speed Train Bogie Based on Multi-Task Learning"}, {"paperId": "164f13c83e0fbec4e1b8dc9b770aee80ab9ff3fa", "title": "Attention Mechanism in Intelligent Fault Diagnosis of Machinery: A Review of Technique and Application"}]}
