{"paperId": "51995cc56060225b966ed89afafbb67195527fee", "publicationVenue": null, "title": "Systematic Literature Review on Big Data Trends", "abstract": "Big Data refers to processing and analyzing huge data sets. Big Data describes large-sized data sets cannot be stored, processed, and analyzed by traditional computing resources and technologies. This paper aims to conduct systematic literature review to explore current research to trends in Big Data. Furthermore, the paper investigates which categories of trends analyzed articles cover, how have trends been changed and what factors affect the shaping of Big Data trends.", "venue": "", "year": 2019, "fieldsOfStudy": ["Computer Science"], "publicationTypes": ["Review"], "publicationDate": "2019-06-15", "journal": {"name": "Journal of Systems Integration", "pages": "2-8", "volume": "10"}, "authors": [{"authorId": "2082277788", "name": "Diana Sharapova"}, {"authorId": "3454927", "name": "Sona Karkoskov\u00e1"}], "citations": []}
