{"paperId": "5d9b46fe060ea7be44ecec3a1fd3a8995206f378", "publicationVenue": {"id": "f1d0ef3d-4e90-41e9-b454-f589a933654f", "name": "Cluster Computing", "type": "journal", "alternate_names": ["Clust Comput"], "issn": "1386-7857", "url": "https://www.springer.com/computer/communication+networks/journal/10586", "alternate_urls": ["https://link.springer.com/journal/10586", "http://www.springer.com/computer/communication+networks/journal/10586"]}, "title": "Efficient deadline-aware scheduling for the analysis of Big Data streams in public Cloud", "abstract": null, "venue": "Cluster Computing", "year": 2019, "fieldsOfStudy": ["Computer Science"], "publicationTypes": ["JournalArticle"], "publicationDate": "2019-02-14", "journal": {"name": "Cluster Computing", "pages": "241-263", "volume": "23"}, "authors": [{"authorId": "1409874289", "name": "Mahmood Mortazavi-Dehkordi"}, {"authorId": "3007108", "name": "K. Zamanifar"}], "citations": [{"paperId": "c6515027597b023ac17099c6cb4fa85cdfaacc25", "title": "Gaussian Adapted Markov Model with Overhauled Fluctuation Analysis-Based Big Data Streaming Model in Cloud."}, {"paperId": "bc0eb55276ada43993eafd6ed349ef3f980fb286", "title": "Prediction-based scheduling techniques for cloud data center\u2019s workload: a systematic review"}, {"paperId": "84617f481cc1a3ebf5f4634fbce8922a52f83865", "title": "Hybrid Algorithm for Resource Aware Predictive Scheduling: A case-study to Human Activity Recognition"}, {"paperId": "55e11dba7d52c4d55bbbe9514838f8f2a4e9bd16", "title": "Job scheduling for big data analytical applications in clouds: A taxonomy study"}, {"paperId": "336ff6e77b9f72821c87517be8297cddbe8f13f4", "title": "Elastic net feature selected multivariate discriminant mapreduce classification"}, {"paperId": "aeb8589a7b36983603fb06e769dfa297accd6a96", "title": "An online algorithm for scheduling big data analysis jobs in cloud environments"}, {"paperId": "6ffa9d997bd772ec8fb3151aeaa21bd71198d14e", "title": "Join queries optimization in the distributed databases using a hybrid multi-objective algorithm"}, {"paperId": "296fde3ff5db3ec345b6a280e42b76ec151a9f99", "title": "Optimization Algorithm and Simulation of Public Resource Emergency Scheduling Based on Wireless Sensor Technology"}, {"paperId": "b78c4f6e49ea469a85bd7d5e669868e58fdc568b", "title": "A multi-level collaborative framework for elastic stream computing systems"}, {"paperId": "eebb97905a0be91b174f0c90b8b8138df77c00de", "title": "OPSA: an optimized prediction based scheduling approach for scientific applications in cloud environment"}, {"paperId": "201701e7db136321a9bc5b996226352262054897", "title": "Self-tuning serverless task farming using proactive elasticity control"}, {"paperId": "e7df89706542ae7ac36cd81ada612eccf0e86536", "title": "Execution cost minimization scheduling algorithms for deadline-constrained parallel applications on heterogeneous clouds"}, {"paperId": "8c7f03c33f91efa738db380ee542e0dd258b748c", "title": "DCHG-TS: a deadline-constrained and cost-effective hybrid genetic algorithm for scientific workflow scheduling in cloud computing"}, {"paperId": "f5bdf65e5c5d14289d2dfbd910f1cef5cc3ba697", "title": "Two-level utilization-based processor allocation for scheduling moldable jobs"}, {"paperId": "712902d0ef1692bbe0f2e0e57f9c94b5ab42dece", "title": "Pipeline-Based Linear Scheduling of Big Data Streams in the Cloud"}]}
