{"paperId": "7012a0feb0f33eb6196f089d52b641563a6e9dc2", "publicationVenue": {"id": "f5e7a63d-0c26-4687-a1bf-ff276da20ecc", "name": "Marine Environmental Research", "type": "journal", "alternate_names": ["Mar Environ Res"], "issn": "0141-1136", "url": "https://www.journals.elsevier.com/marine-environmental-research/", "alternate_urls": ["http://www.sciencedirect.com/science/journal/01411136"]}, "title": "Marine macroinvertebrate ecosystem services under changing conditions of seagrasses and mangroves.", "abstract": null, "venue": "Marine Environmental Research", "year": 2023, "fieldsOfStudy": ["Medicine"], "publicationTypes": ["JournalArticle"], "publicationDate": "2023-05-01", "journal": {"name": "Marine environmental research", "pages": "\n          106026\n        ", "volume": "189"}, "authors": [{"authorId": "119655839", "name": "Frederick Asante"}, {"authorId": "40220759", "name": "M. S\u00e3o Bento"}, {"authorId": "6182738", "name": "Stefanie Broszeit"}, {"authorId": "144978581", "name": "S. Bandeira"}, {"authorId": "2141162950", "name": "S\u00e1dia Chitar\u00e1-Nhandimo"}, {"authorId": "1481197052", "name": "M. Amone\u2010Mabuto"}, {"authorId": "40060733", "name": "A. M. Correia"}], "citations": []}
