{"paperId": "86f5c88a276cc45a5d346070e56ea823432906b4", "publicationVenue": {"id": "2172c211-c90f-4375-888e-587b3f9d8e1a", "name": "Location Science", "type": "journal", "alternate_names": ["Locat Sci"], "issn": "0966-8349", "url": "http://www.sciencedirect.com/science/journal/09668349"}, "title": "Location and Geographic Information Systems", "abstract": null, "venue": "Location Science", "year": 2019, "fieldsOfStudy": ["Computer Science"], "publicationTypes": null, "publicationDate": null, "journal": {"name": "Location Science"}, "authors": [{"authorId": "2724666", "name": "B. Bozkaya"}, {"authorId": "48948465", "name": "G. Bruno"}, {"authorId": "2575432", "name": "I. Giannikos"}], "citations": [{"paperId": "bbcc3bed0cda681d2ac01b8518407418ee4f0679", "title": "Facility Location in Logistics and Transportation: An enduring relationship"}]}
