{"paperId": "8a53defb56d4fd9a4d616504aaf62c6679cc6580", "publicationVenue": {"id": "45ab97d0-7ed0-42c0-bbc5-d4e3e1b8cec3", "name": "Lecture Notes in Networks and Systems", "alternate_names": ["Lect Note Netw Syst"], "issn": "2367-3389", "alternate_issns": ["2367-3370"], "url": "https://www.springer.com/series/15179"}, "title": "Storage Mechanism for Heterogeneous Streamed Sensor Data", "abstract": null, "venue": "Lecture Notes in Networks and Systems", "year": 2022, "fieldsOfStudy": null, "publicationTypes": null, "publicationDate": null, "journal": {"name": "Lecture Notes in Networks and Systems"}, "authors": [{"authorId": "35708548", "name": "J. RubyDinakar"}, {"authorId": "9139663", "name": "S. Vagdevi"}], "citations": []}
