{"paperId": "9ae303f0688c5416e3e7e84c49b63a3e7819caf7", "publicationVenue": {"id": "d6a70d34-0855-4e32-aa47-d6ab631309c3", "name": "CAAI Transactions on Intelligence Technology", "type": "journal", "alternate_names": ["CAAI Trans Intell Technol"], "issn": "2468-2322", "url": "https://www.sciencedirect.com/journal/caai-transactions-on-intelligence-technology", "alternate_urls": ["https://digital-library.theiet.org/content/journals/trit"]}, "title": "Deep learning in crowd counting: A survey", "abstract": null, "venue": "CAAI Transactions on Intelligence Technology", "year": 2023, "fieldsOfStudy": null, "publicationTypes": ["JournalArticle", "Review"], "publicationDate": "2023-06-14", "journal": {"name": "CAAI Transactions on Intelligence Technology"}, "authors": [{"authorId": "15592955", "name": "Lijia Deng"}, {"authorId": "1729394282", "name": "Qinghua Zhou"}, {"authorId": "7488474", "name": "Shuihua Wang"}, {"authorId": "1704580", "name": "J. G\u00f3rriz"}, {"authorId": "2211918106", "name": "Yudong Zhang"}], "citations": [{"paperId": "7e9f04b66e7c7c4e44ec534c9a889a0d9b5a8331", "title": "An Excess Kurtosis People Counting System Based on 1DCNN-LSTM Using Impulse Radio Ultra-Wide Band Radar Signals"}]}
