{"paperId": "d3351df715fcb26cfdc092cbd403f450ea4cb49a", "publicationVenue": {"id": "26ed29a9-64ce-4d6c-9024-8b022fd2fe22", "name": "Journal of Supercomputing", "type": "journal", "alternate_names": ["The Journal of Supercomputing", "J Supercomput"], "issn": "0920-8542", "url": "http://www.springer.com/computer/programming/journal/11227", "alternate_urls": ["https://link.springer.com/journal/11227", "https://www.springer.com/computer/swe/journal/11227?changeHeader"]}, "title": "A new Apache Spark-based framework for big data streaming forecasting in IoT networks", "abstract": null, "venue": "Journal of Supercomputing", "year": 2023, "fieldsOfStudy": ["Medicine", "Computer Science"], "publicationTypes": ["JournalArticle"], "publicationDate": "2023-02-21", "journal": {"name": "The Journal of Supercomputing", "pages": "11078 - 11100", "volume": "79"}, "authors": [{"authorId": "2209139966", "name": "Antonio M. Fern\u00e1ndez-G\u00f3mez"}, {"authorId": "1405773847", "name": "David Guti\u00e9rrez-Avil\u00e9s"}, {"authorId": "51352689", "name": "A. Troncoso"}, {"authorId": "1397728402", "name": "F. Mart\u00ednez-\u00c1lvarez"}], "citations": [{"paperId": "a3f024adb39ecfa4fdb098b435545c396e26a112", "title": "Building Advanced Web Applications Using Data Ingestion and Data Processing Tools"}, {"paperId": "9eb2baad7c7fb5048da3f02a7fea3f19fed896e5", "title": "Apache Spark Big data Analysis, Performance Tuning, and Spark Application Optimization"}, {"paperId": "c6143867973c600ce793581e4fa7242da319489f", "title": "Geological Disaster Rainfall Measurement System Based on Piezoelectric Sensing Technology"}, {"paperId": "c533f4ab7e044ad389966cd91b58864ac36dd6bc", "title": "Complementary Architecture of E-Learning Path Personalization and Optimization"}, {"paperId": "a7d8e5f60e4241a8aa4a02656302ccb4624e85ef", "title": "Real-Time Analytics: Concepts, Architectures, and ML/AI Considerations"}]}
